walkmate/__init__.py
walkmate/tree.py
walkmate-1.5.0.dist-info/METADATA
walkmate-1.5.0.dist-info/WHEEL
walkmate-1.5.0.dist-info/licenses/LICENSE.md
walkmate-1.5.0.dist-info/RECORD
