Metadata-Version: 2.3
Name: walkmate
Version: 1.5.0
Summary: Traverse the file tree.
Project-URL: Homepage, https://github.com/JoelLefkowitz/walkmate
Author-email: Joel Lefkowitz <joellefkowitz@hotmail.com>
License: # MIT License
License-File: LICENSE.md
Keywords: filesystem,traverse,tree,walk
Classifier: License :: OSI Approved :: MIT License
Classifier: Programming Language :: Python :: 3.6
Classifier: Programming Language :: Python :: 3.7
Classifier: Programming Language :: Python :: 3.8
Requires-Python: >=3.6
